databricksapi/Clusters.py
databricksapi/DBFS.py
databricksapi/Databricks.py
databricksapi/Groups.py
databricksapi/InstanceProfile.py
databricksapi/Jobs.py
databricksapi/Libraries.py
databricksapi/SCIM.py
databricksapi/Secrets.py
databricksapi/Token.py
databricksapi/Workspace.py
databricksapi/__init__.py
databricksapi-1.1.1.dist-info/LICENSE
databricksapi-1.1.1.dist-info/METADATA
databricksapi-1.1.1.dist-info/WHEEL
databricksapi-1.1.1.dist-info/top_level.txt
databricksapi-1.1.1.dist-info/RECORD
